strava_offline/__init__.py
strava_offline/__main__.py
strava_offline/cli.py
strava_offline/config.py
strava_offline/config_file.py
strava_offline/gpx.py
strava_offline/py.typed
strava_offline/redirect_server.py
strava_offline/reports.py
strava_offline/sqlite.py
strava_offline/strava.py
strava_offline/sync.py
strava_offline-1.1.0.dist-info/LICENSE
strava_offline-1.1.0.dist-info/METADATA
strava_offline-1.1.0.dist-info/WHEEL
strava_offline-1.1.0.dist-info/entry_points.txt
strava_offline-1.1.0.dist-info/top_level.txt
strava_offline-1.1.0.dist-info/RECORD
