Metadata-Version: 2.1
Name: strava-offline
Version: 1.1.0
Summary: Leep a local mirror of Strava activities for further analysis/processing
Author-email: Tomáš Janoušek <tomi@nomi.cz>
License: MIT
Project-URL: Homepage, https://github.com/liskin/strava-offline
Classifier: Development Status :: 5 - Production/Stable
Classifier: Environment :: Console
Classifier: License :: OSI Approved :: MIT License
Classifier: Operating System :: OS Independent
Classifier: Programming Language :: Python :: 3.8
Classifier: Programming Language :: Python :: 3.9
Classifier: Programming Language :: Python :: 3.10
Classifier: Programming Language :: Python :: 3.11
Classifier: Programming Language :: Python :: 3.12
Classifier: Topic :: Database
Classifier: Topic :: Utilities
Requires-Python: ~=3.8
License-File: LICENSE
Requires-Dist: PyYAML
Requires-Dist: bottle
Requires-Dist: click ~=8.0
Requires-Dist: click-config-file
Requires-Dist: click-option-group
Requires-Dist: platformdirs >=2.1
Requires-Dist: requests
Requires-Dist: requests-oauthlib
Requires-Dist: tabulate
Requires-Dist: typing-extensions
Requires-Dist: importlib-metadata ; python_version < "3.10"
Provides-Extra: dev
Requires-Dist: build >=0.7 ; extra == 'dev'
Requires-Dist: cram ; extra == 'dev'
Requires-Dist: flake8 ; extra == 'dev'
Requires-Dist: isort >=5.0 ; extra == 'dev'
Requires-Dist: mypy >=0.900 ; extra == 'dev'
Requires-Dist: pyflakes >=2.2.0 ; extra == 'dev'
Requires-Dist: twine ; extra == 'dev'
Requires-Dist: types-PyYAML ; extra == 'dev'
Requires-Dist: types-requests ; extra == 'dev'
Requires-Dist: types-tabulate ; extra == 'dev'
Provides-Extra: test
Requires-Dist: pytest ; extra == 'test'
Requires-Dist: pytest-recording ; extra == 'test'
Requires-Dist: vcrpy >=4.3.1 ; extra == 'test'
